tekton_neat/__init__.py
tekton_neat/cli.py
tekton_neat/tekton_neat.py
tekton_neat-0.3.0.dist-info/AUTHORS.rst
tekton_neat-0.3.0.dist-info/LICENSE
tekton_neat-0.3.0.dist-info/METADATA
tekton_neat-0.3.0.dist-info/WHEEL
tekton_neat-0.3.0.dist-info/entry_points.txt
tekton_neat-0.3.0.dist-info/top_level.txt
tekton_neat-0.3.0.dist-info/RECORD
